enijo/connector/__init__.py
enijo/connector/builders.py
enijo/connector/data_repository_connector.py
enijo/connector/draft_file_connector.py
enijo/connector/draft_record_connector.py
enijo/connector/exceptions.py
enijo/connector/file_connector.py
enijo/connector/record_connector.py
enijo/connector/rest_api_client_extras.py
enijo/connector/rest_api_client/__init__.py
enijo/connector/rest_api_client/client.py
enijo/connector/rest_api_client/types.py
enijo/connector/rest_api_client/api/__init__.py
enijo/connector/rest_api_client/api/draft_files/__init__.py
enijo/connector/rest_api_client/api/draft_files/records_id_draft_files_filename_commit_post.py
enijo/connector/rest_api_client/api/draft_files/records_id_draft_files_filename_content_put.py
enijo/connector/rest_api_client/api/draft_files/records_id_draft_files_list.py
enijo/connector/rest_api_client/api/draft_files/records_id_draft_files_post.py
enijo/connector/rest_api_client/api/drafts/__init__.py
enijo/connector/rest_api_client/api/drafts/records_create.py
enijo/connector/rest_api_client/api/drafts/records_id_draft_actions_publish_post.py
enijo/connector/rest_api_client/api/record_files/__init__.py
enijo/connector/rest_api_client/api/record_files/records_id_files_filename_content_get.py
enijo/connector/rest_api_client/api/record_files/records_id_files_get.py
enijo/connector/rest_api_client/api/records/__init__.py
enijo/connector/rest_api_client/api/records/records_id_get.py
enijo/connector/rest_api_client/api/versions/__init__.py
enijo/connector/rest_api_client/api/versions/records_id_versions_post.py
enijo/connector/rest_api_client/models/__init__.py
enijo/connector/rest_api_client/models/access_information.py
enijo/connector/rest_api_client/models/access_information_embargo.py
enijo/connector/rest_api_client/models/access_information_files.py
enijo/connector/rest_api_client/models/access_information_record.py
enijo/connector/rest_api_client/models/affiliation_identifier.py
enijo_connector-0.4.0.dist-info/AUTHORS
enijo_connector-0.4.0.dist-info/LICENSE
enijo_connector-0.4.0.dist-info/METADATA
enijo_connector-0.4.0.dist-info/WHEEL
enijo_connector-0.4.0.dist-info/top_level.txt
enijo_connector-0.4.0.dist-info/RECORD
