Metadata-Version: 2.1
Name: enijo-connector
Version: 0.4.0
Summary: Python Connector for Invinio-RDM Data Repository
Home-page: https://gitlab.com/qyanu/enijo-connector
License: MIT
Platform: UNKNOWN
Requires: beautifulsoup4
Requires: httpx
Requires: openapi
Requires: python_dateutil
Requires: pyyaml
Requires: requests
Requires: sphinx
License-File: LICENSE
License-File: AUTHORS
